src/test/mux2_1.sv
module mux2_1(out, i0, i1, sel);
  output logic out;
  input logic i0, i1, sel;
  assign out = (i1 & sel) | (i0 & ~sel);
endmodule

src/test/mux2_1_tb.sv
`timescale 1ns / 1ps
`default_nettype none
module mux2_1_tb();
    logic i0, i1, sel;
    logic out;
    mux2_1 dut (.out, .i0, .i1, .sel);

    initial begin
        $dumpfile("example2.vcd"); //file to store value change dump (vcd)
        $dumpvars(0,mux2_1_tb); //store everything at the current level and below

        sel=0; i0=0; i1=0; #10;
        sel=0; i0=0; i1=1; #10;
        sel=0; i0=1; i1=0; #10;
        sel=0; i0=1; i1=1; #10;
        sel=1; i0=0; i1=0; #10;
        sel=1; i0=0; i1=1; #10;
        sel=1; i0=1; i1=0; #10;
        sel=1; i0=1; i1=1; #10;
    end
endmodule

src/test/example2.vcd
$date
	Thu Jun 27 17:12:26 2024
$end
$version
	Icarus Verilog
$end
$timescale
	1ps
$end
$scope module mux2_1_tb $end
$var wire 1 ! out $end
$var reg 1 " i0 $end
$var reg 1 # i1 $end
$var reg 1 $ sel $end
$scope module dut $end
$var wire 1 " i0 $end
$var wire 1 # i1 $end
$var wire 1 ! out $end
$var wire 1 $ sel $end
$upscope $end
$upscope $end
$enddefinitions $end
$comment Show the parameter values. $end
$dumpall
$end
#0
$dumpvars
0$
0#
0"
0!
$end
#10000
1#
#20000
1!
0#
1"
#30000
1#
#40000
0!
0#
0"
1$
#50000
1!
1#
#60000
0!
0#
1"
#70000
1!
1#
