src/test/example.sv
`timescale 1ns / 1ps
`default_nettype none

// a simple module that will increment c_out on the clock edge if a_in < b_in
// otherwise, c_out doesn't change.
module example (
        input wire          clk_in,
        input wire          rst_in,
        input wire [5:0]    a_in,
        input wire [5:0]    b_in,
        output logic [4:0]  c_out);

  always_ff @(posedge clk_in) begin
    if (rst_in) begin
      // reset to 0 
      c_out <= 0;
    end else begin
      c_out <= (a_in > b_in) ? c_out : c_out + 1;
    end
  end
endmodule


module example_tb();
    logic clk_in;
    logic rst_in;
    logic [5:0] a_in, b_in;
    logic [4:0] c_out;

    example uut(  .clk_in(clk_in),
                  .rst_in(rst_in),
                  .a_in(a_in),
                  .b_in(b_in),
                  .c_out(c_out));

    always begin
        #5;  //every 5 ns switch...so period of clock is 10 ns...100 MHz clock
        clk_in = !clk_in;
    end

    //initial block...this is our test simulation
    initial begin
        $dumpfile("example.vcd"); //file to store value change dump (vcd)
        $dumpvars(0,example_tb); //store everything at the current level and below
        $display("Starting Sim"); //print nice message at start
        clk_in = 0; //0 is generally a safe value to initialize with and not specify size
        rst_in = 0;
        a_in = 0;
        b_in = 0;
        #10
        rst_in = 1; //always good to reset
        #10
        rst_in = 0;
        $display("a_in    b_in    c_out");
        for (integer i=0; i<256; i = i+1)begin
          for (integer j=0; j<256; j= j+1)begin
            a_in = i;
            b_in = j;
            #10; //wait
            $display("%8b %8b %5c",a_in, b_in, c_out); //print values C-style formatting
          end
        end
        $display("Finishing Sim"); //print nice message at end
        $finish;
    end
endmodule

`default_nettype wire

src/test/example.vcd
$date
	Fri Aug 30 12:26:26 2024
$end
$version
	Icarus Verilog
$end
$timescale
	1ps
$end
$scope module example_tb $end
$var wire 5 ! c_out [4:0] $end
$var reg 6 " a_in [5:0] $end
$var reg 6 # b_in [5:0] $end
$var reg 1 $ clk_in $end
$var reg 1 % rst_in $end
$scope module uut $end
$var wire 6 & a_in [5:0] $end
$var wire 6 ' b_in [5:0] $end
$var wire 1 $ clk_in $end
$var wire 1 % rst_in $end
$var reg 5 ( c_out [4:0] $end
$upscope $end
$scope begin $ivl_for_loop0 $end
$var integer 32 ) i [31:0] $end
$scope begin $ivl_for_loop1 $end
$var integer 32 * j [31:0] $end
$upscope $end
$upscope $end
$upscope $end
$enddefinitions $end
$comment Show the parameter values. $end
$dumpall
$end
#0
$dumpvars
bx *
bx )
bx (
b0 '
b0 &
0%
0$
b0 #
b0 "
bx !
$end
#5000
1$
#10000
0$
1%
#15000
b0 !
b0 (
1$
#20000
0$
b0 *
b0 )
0%
#25000
b1 !
b1 (
1$
#30000
0$
b1 #
b1 '
b1 *
#35000
b10 !
b10 (
1$
#40000
0$
b10 #
b10 '
b10 *
#45000
b11 !
b11 (
1$
#50000
0$
b11 #
b11 '
b11 *
#55000
b100 !
b100 (
1$
#60000
0$
b100 #
b100 '
b100 *
#65000
b101 !
b101 (
1$
#70000
0$
b101 #
b101 '
b101 *
#75000
b110 !
b110 (
1$
#80000
0$
b110 #
b110 '
b110 *
#85000
b111 !
b111 (
1$
#90000
0$
b111 #
b111 '
b111 *
#95000
b1000 !
b1000 (
1$
#100000
0$
b1000 #
b1000 '
b1000 *
#105000
b1001 !
b1001 (
1$
#110000
0$
b1001 #
b1001 '
b1001 *
#115000
b1010 !
b1010 (
1$
#120000
0$
b1010 #
b1010 '
b1010 *
#125000
b1011 !
b1011 (
1$
#130000
0$
b1011 #
b1011 '
b1011 *
#135000
b1100 !
b1100 (
1$
#140000
0$
b1100 #
b1100 '
b1100 *
#145000
b1101 !
b1101 (
1$
#150000
0$
b1101 #
b1101 '
b1101 *
#155000
b1110 !
b1110 (
1$
#160000
0$
b1110 #
b1110 '
b1110 *
#165000
b1111 !
b1111 (
1$
#170000
0$
b1111 #
b1111 '
b1111 *
#175000
b10000 !
b10000 (
1$
#180000
0$
b10000 #
b10000 '
b10000 *
#185000
b10001 !
b10001 (
1$
#190000
0$
b10001 #
b10001 '
b10001 *
#195000
b10010 !
b10010 (
1$
#200000
0$
b10010 #
b10010 '
b10010 *
#205000
b10011 !
b10011 (
1$
#210000
0$
b10011 #
b10011 '
b10011 *
#215000
b10100 !
b10100 (
1$
#220000
0$
b10100 #
b10100 '
b10100 *
#225000
b10101 !
b10101 (
1$
#230000
0$
b10101 #
b10101 '
b10101 *
#235000
b10110 !
b10110 (
1$
#240000
0$
b10110 #
b10110 '
b10110 *
#245000
b10111 !
b10111 (
1$
#250000
0$
b10111 #
b10111 '
b10111 *
#255000
b11000 !
b11000 (
1$
#260000
0$
b11000 #
b11000 '
b11000 *
#265000
b11001 !
b11001 (
1$
#270000
0$
b11001 #
b11001 '
b11001 *
#275000
b11010 !
b11010 (
1$
#280000
0$
b11010 #
b11010 '
b11010 *
#285000
b11011 !
b11011 (
1$
#290000
0$
b11011 #
b11011 '
b11011 *
#295000
b11100 !
b11100 (
1$
#300000
0$
b11100 #
b11100 '
b11100 *
#305000
b11101 !
b11101 (
1$
#310000
0$
b11101 #
b11101 '
b11101 *
#315000
b11110 !
b11110 (
1$
#320000
0$
b11110 #
b11110 '
b11110 *
#325000
b11111 !
b11111 (
1$
#330000
0$
b11111 #
b11111 '
b11111 *
#335000
b0 !
b0 (
1$
#340000
0$
b100000 #
b100000 '
b100000 *
#345000
b1 !
b1 (
1$
#350000
0$
b100001 #
b100001 '
b100001 *
#355000
b10 !
b10 (
1$
#360000
0$
b100010 #
b100010 '
b100010 *
#365000
b11 !
b11 (
1$
#370000
0$
b100011 #
b100011 '
b100011 *
#375000
b100 !
b100 (
1$
#380000
0$
b100100 #
b100100 '
b100100 *
#385000
b101 !
b101 (
1$
#390000
0$
b100101 #
b100101 '
b100101 *
#395000
b110 !
b110 (
1$
#400000
0$
b100110 #
b100110 '
b100110 *
#405000
b111 !
b111 (
1$
#410000
0$
b100111 #
b100111 '
b100111 *
#415000
b1000 !
b1000 (
1$
#420000
0$
b101000 #
b101000 '
b101000 *
#425000
b1001 !
b1001 (
1$
#430000
0$
b101001 #
b101001 '
b101001 *
#435000
b1010 !
b1010 (
1$
#440000
0$
b101010 #
b101010 '
b101010 *
#445000
b1011 !
b1011 (
1$
#450000
0$
b101011 #
b101011 '
b101011 *
#455000
b1100 !
b1100 (
1$
#460000
0$
b101100 #
b101100 '
b101100 *
#465000
b1101 !
b1101 (
1$
#470000
0$
b101101 #
b101101 '
b101101 *
#475000
b1110 !
b1110 (
1$
#480000
0$
b101110 #
b101110 '
b101110 *
#485000
b1111 !
b1111 (
1$
#490000
0$
b101111 #
b101111 '
b101111 *
#495000
b10000 !
b10000 (
1$
#500000
0$
b110000 #
b110000 '
b110000 *
#505000
b10001 !
b10001 (
1$
#510000
0$
b110001 #
b110001 '
b110001 *
#515000
b10010 !
b10010 (
1$
#520000
0$
b110010 #
b110010 '
b110010 *
#525000
b10011 !
b10011 (
1$
#530000
0$
b110011 #
b110011 '
b110011 *
#535000
b10100 !
b10100 (
1$
#540000
0$
b110100 #
b110100 '
b110100 *
#545000
b10101 !
b10101 (
1$
#550000
0$
b110101 #
b110101 '
b110101 *
#555000
b10110 !
b10110 (
1$
#560000
0$
b110110 #
b110110 '
b110110 *
#565000
b10111 !
b10111 (
1$
#570000
0$
b110111 #
b110111 '
b110111 *
#575000
b11000 !
b11000 (
1$
#580000
0$
b111000 #
b111000 '
b111000 *
#585000
b11001 !
b11001 (
1$
#590000
0$
b111001 #
b111001 '
b111001 *
#595000
b11010 !
b11010 (
1$
#600000
0$
b111010 #
b111010 '
b111010 *
#605000
b11011 !
b11011 (
1$
#610000
0$
b111011 #
b111011 '
b111011 *
#615000
b11100 !
b11100 (
1$
#620000
0$
b111100 #
b111100 '
b111100 *
#625000
b11101 !
b11101 (
1$
#630000
0$
b111101 #
b111101 '
b111101 *
#635000
b11110 !
b11110 (
1$
#640000
0$
b111110 #
b111110 '
b111110 *
#645000
b11111 !
b11111 (
1$
#650000
0$
b111111 #
b111111 '
b111111 *
#655000
b0 !
b0 (
1$
#660000
0$
b0 #
b0 '
b1000000 *
#665000
b1 !
b1 (
1$
#670000
0$
b1 #
b1 '
b1000001 *
#675000
b10 !
b10 (
1$
#680000
0$
b10 #
b10 '
b1000010 *
#685000
b11 !
b11 (
1$
#690000
0$
b11 #
b11 '
b1000011 *
#695000
b100 !
b100 (
1$
#700000
0$
b100 #
b100 '
b1000100 *
#705000
b101 !
b101 (
1$
#710000
0$
b101 #
b101 '
b1000101 *
#715000
b110 !
b110 (
1$
#720000
0$
b110 #
b110 '
b1000110 *
#725000
b111 !
b111 (
1$
#730000
0$
b111 #
b111 '
b1000111 *
#735000
b1000 !
b1000 (
1$
#740000
0$
b1000 #
b1000 '
b1001000 *
#745000
b1001 !
b1001 (
1$
#750000
0$
b1001 #
b1001 '
b1001001 *
#755000
b1010 !
b1010 (
1$
#760000
0$
b1010 #
b1010 '
b1001010 *
#765000
b1011 !
b1011 (
1$
#770000
0$
b1011 #
b1011 '
b1001011 *
#775000
b1100 !
b1100 (
1$
#780000
0$
b1100 #
b1100 '
b1001100 *
#785000
b1101 !
b1101 (
1$
#790000
0$
b1101 #
b1101 '
b1001101 *
#795000
b1110 !
b1110 (
1$
#800000
0$
b1110 #
b1110 '
b1001110 *
#805000
b1111 !
b1111 (
1$
#810000
0$
b1111 #
b1111 '
b1001111 *
#815000
b10000 !
b10000 (
1$
#820000
0$
b10000 #
b10000 '
b1010000 *
#825000
b10001 !
b10001 (
1$
#830000
0$
b10001 #
b10001 '
b1010001 *
#835000
b10010 !
b10010 (
1$
#840000
0$
b10010 #
b10010 '
b1010010 *
#845000
b10011 !
b10011 (
1$
#850000
0$
b10011 #
b10011 '
b1010011 *
#855000
b10100 !
b10100 (
1$
#860000
0$
b10100 #
b10100 '
b1010100 *
#865000
b10101 !
b10101 (
1$
#870000
0$
b10101 #
b10101 '
b1010101 *
#875000
b10110 !
b10110 (
1$
#880000
0$
b10110 #
b10110 '
b1010110 *
#885000
b10111 !
b10111 (
1$
#890000
0$
b10111 #
b10111 '
b1010111 *
#895000
b11000 !
b11000 (
1$
#900000
0$
b11000 #
b11000 '
b1011000 *
#905000
b11001 !
b11001 (
1$
#910000
0$
b11001 #
b11001 '
b1011001 *
#915000
b11010 !
b11010 (
1$
#920000
0$
b11010 #
b11010 '
b1011010 *
#925000
b11011 !
b11011 (
1$
#930000
0$
b11011 #
b11011 '
b1011011 *
#935000
b11100 !
b11100 (
1$
#940000
0$
b11100 #
b11100 '
b1011100 *
#945000
b11101 !
b11101 (
1$
#950000
0$
b11101 #
b11101 '
b1011101 *
#955000
b11110 !
b11110 (
1$
#960000
0$
b11110 #
b11110 '
b1011110 *
#965000
b11111 !
b11111 (
1$
#970000
0$
b11111 #
b11111 '
b1011111 *
#975000
b0 !
b0 (
1$
#980000
0$
b100000 #
b100000 '
b1100000 *
#985000
b1 !
b1 (
1$
#990000
0$
b100001 #
b100001 '
b1100001 *
#995000
b10 !
b10 (
1$
#1000000
0$
b100010 #
b100010 '
b1100010 *
#1005000
b11 !
b11 (
1$
#1010000
0$
b100011 #
b100011 '
b1100011 *
#1015000
b100 !
b100 (
1$
#1020000
0$
b100100 #
b100100 '
b1100100 *
#1025000
b101 !
b101 (
1$
#1030000
0$
b100101 #
b100101 '
b1100101 *
#1035000
b110 !
b110 (
1$
#1040000
0$
b100110 #
b100110 '
b1100110 *
#1045000
b111 !
b111 (
1$
#1050000
0$
b100111 #
b100111 '
b1100111 *
#1055000
b1000 !
b1000 (
1$
#1060000
0$
b101000 #
b101000 '
b1101000 *
#1065000
b1001 !
b1001 (
1$
#1070000
0$
b101001 #
b101001 '
b1101001 *
#1075000
b1010 !
b1010 (
1$
#1080000
0$
b101010 #
b101010 '
b1101010 *
#1085000
b1011 !
b1011 (
1$
#1090000
0$
b101011 #
b101011 '
b1101011 *
#1095000
b1100 !
b1100 (
1$
#1100000
0$
b101100 #
b101100 '
b1101100 *
#1105000
b1101 !
b1101 (
1$
#1110000
0$
b101101 #
b101101 '
b1101101 *
#1115000
b1110 !
b1110 (
1$
#1120000
0$
b101110 #
b101110 '
b1101110 *
#1125000
b1111 !
b1111 (
1$
#1130000
0$
b101111 #
b101111 '
b1101111 *
#1135000
b10000 !
b10000 (
1$
#1140000
0$
b110000 #
b110000 '
b1110000 *
#1145000
b10001 !
b10001 (
1$
#1150000
0$
b110001 #
b110001 '
b1110001 *
#1155000
b10010 !
b10010 (
1$
#1160000
0$
b110010 #
b110010 '
b1110010 *
#1165000
b10011 !
b10011 (
1$
#1170000
0$
b110011 #
b110011 '
b1110011 *
#1175000
b10100 !
b10100 (
1$
#1180000
0$
b110100 #
b110100 '
b1110100 *
#1185000
b10101 !
b10101 (
1$
#1190000
0$
b110101 #
b110101 '
b1110101 *
#1195000
b10110 !
b10110 (
1$
#1200000
0$
b110110 #
b110110 '
b1110110 *
#1205000
b10111 !
b10111 (
1$
#1210000
0$
b110111 #
b110111 '
b1110111 *
#1215000
b11000 !
b11000 (
1$
#1220000
0$
b111000 #
b111000 '
b1111000 *
#1225000
b11001 !
b11001 (
1$
#1230000
0$
b111001 #
b111001 '
b1111001 *
#1235000
b11010 !
b11010 (
1$
#1240000
0$
b111010 #
b111010 '
b1111010 *
#1245000
b11011 !
b11011 (
1$
#1250000
0$
b111011 #
b111011 '
b1111011 *
#1255000
b11100 !
b11100 (
1$
#1260000
0$
b111100 #
b111100 '
b1111100 *
#1265000
b11101 !
b11101 (
1$
#1270000
0$
b111101 #
b111101 '
b1111101 *
#1275000
b11110 !
b11110 (
1$
#1280000
0$
b111110 #
b111110 '
b1111110 *
#1285000
b11111 !
b11111 (
1$
#1290000
0$
b111111 #
b111111 '
b1111111 *
#1295000
b0 !
b0 (
1$
#1300000
0$
b0 #
b0 '
b10000000 *
#1305000
b1 !
b1 (
1$
#1310000
0$
b1 #
b1 '
b10000001 *
#1315000
b10 !
b10 (
1$
#1320000
0$
b10 #
b10 '
b10000010 *
#1325000
b11 !
b11 (
1$
#1330000
0$
b11 #
b11 '
b10000011 *
#1335000
b100 !
b100 (
1$
#1340000
0$
b100 #
b100 '
b10000100 *
#1345000
b101 !
b101 (
1$
#1350000
0$
b101 #
b101 '
b10000101 *
#1355000
b110 !
b110 (
1$
#1360000
0$
b110 #
b110 '
b10000110 *
#1365000
b111 !
b111 (
1$
#1370000
0$
b111 #
b111 '
b10000111 *
#1375000
b1000 !
b1000 (
1$
#1380000
0$
b1000 #
b1000 '
b10001000 *
#1385000
b1001 !
b1001 (
1$
#1390000
0$
b1001 #
b1001 '
b10001001 *
#1395000
b1010 !
b1010 (
1$
#1400000
0$
b1010 #
b1010 '
b10001010 *
#1405000
b1011 !
b1011 (
1$
#1410000
0$
b1011 #
b1011 '
b10001011 *
#1415000
b1100 !
b1100 (
1$
#1420000
0$
b1100 #
b1100 '
b10001100 *
#1425000
b1101 !
b1101 (
1$
#1430000
0$
b1101 #
b1101 '
b10001101 *
#1435000
b1110 !
b1110 (
1$
#1440000
0$
b1110 #
b1110 '
b10001110 *
#1445000
b1111 !
b1111 (
1$
#1450000
0$
b1111 #
b1111 '
b10001111 *
#1455000
b10000 !
b10000 (
1$
#1460000
0$
b10000 #
b10000 '
b10010000 *
#1465000
b10001 !
b10001 (
1$
#1470000
0$
b10001 #
b10001 '
b10010001 *
#1475000
b10010 !
b10010 (
1$
#1480000
0$
b10010 #
b10010 '
b10010010 *
#1485000
b10011 !
b10011 (
1$
#1490000
0$
b10011 #
b10011 '
b10010011 *
#1495000
b10100 !
b10100 (
1$
#1500000
0$
b10100 #
b10100 '
b10010100 *
#1505000
b10101 !
b10101 (
1$
#1510000
0$
b10101 #
b10101 '
b10010101 *
#1515000
b10110 !
b10110 (
1$
#1520000
0$
b10110 #
b10110 '
b10010110 *
#1525000
b10111 !
b10111 (
1$
#1530000
0$
b10111 #
b10111 '
b10010111 *
#1535000
b11000 !
b11000 (
1$
#1540000
0$
b11000 #
b11000 '
b10011000 *
#1545000
b11001 !
b11001 (
1$
#1550000
0$
b11001 #
b11001 '
b10011001 *
#1555000
b11010 !
b11010 (
1$
#1560000
0$
b11010 #
b11010 '
b10011010 *
#1565000
b11011 !
b11011 (
1$
#1570000
0$
b11011 #
b11011 '
b10011011 *
#1575000
b11100 !
b11100 (
1$
#1580000
0$
b11100 #
b11100 '
b10011100 *
#1585000
b11101 !
b11101 (
1$
#1590000
0$
b11101 #
b11101 '
b10011101 *
#1595000
b11110 !
b11110 (
1$
#1600000
0$
b11110 #
b11110 '
b10011110 *
#1605000
b11111 !
b11111 (
1$
#1610000
0$
b11111 #
b11111 '
b10011111 *
#1615000
b0 !
b0 (
1$
#1620000
0$
b100000 #
b100000 '
b10100000 *
#1625000
b1 !
b1 (
1$
#1630000
0$
b100001 #
b100001 '
b10100001 *
#1635000
b10 !
b10 (
1$
#1640000
0$
b100010 #
b100010 '
b10100010 *
#1645000
b11 !
b11 (
1$
#1650000
0$
b100011 #
b100011 '
b10100011 *
#1655000
b100 !
b100 (
1$
#1660000
0$
b100100 #
b100100 '
b10100100 *
#1665000
b101 !
b101 (
1$
#1670000
0$
b100101 #
b100101 '
b10100101 *
#1675000
b110 !
b110 (
1$
#1680000
0$
b100110 #
b100110 '
b10100110 *
#1685000
b111 !
b111 (
1$
#1690000
0$
b100111 #
b100111 '
b10100111 *
#1695000
b1000 !
b1000 (
1$
#1700000
0$
b101000 #
b101000 '
b10101000 *
#1705000
b1001 !
b1001 (
1$
#1710000
0$
b101001 #
b101001 '
b10101001 *
#1715000
b1010 !
b1010 (
1$
#1720000
0$
b101010 #
b101010 '
b10101010 *
#1725000
b1011 !
b1011 (
1$
#1730000
0$
b101011 #
b101011 '
b10101011 *
#1735000
b1100 !
b1100 (
1$
#1740000
0$
b101100 #
b101100 '
b10101100 *
#1745000
b1101 !
b1101 (
1$
#1750000
0$
b101101 #
b101101 '
b10101101 *
#1755000
b1110 !
b1110 (
1$
#1760000
0$
b101110 #
b101110 '
b10101110 *
#1765000
b1111 !
b1111 (
1$
#1770000
0$
b101111 #
b101111 '
b10101111 *
#1775000
b10000 !
b10000 (
1$
#1780000
0$
b110000 #
b110000 '
b10110000 *
#1785000
b10001 !
b10001 (
1$
#1790000
0$
b110001 #
b110001 '
b10110001 *
#1795000
b10010 !
b10010 (
1$
#1800000
0$
b110010 #
b110010 '
b10110010 *
#1805000
b10011 !
b10011 (
1$
#1810000
0$
b110011 #
b110011 '
b10110011 *
#1815000
b10100 !
b10100 (
1$
#1820000
0$
b110100 #
b110100 '
b10110100 *
#1825000
b10101 !
b10101 (
1$
#1830000
0$
b110101 #
b110101 '
b10110101 *
#1835000
b10110 !
b10110 (
1$
#1840000
0$
b110110 #
b110110 '
b10110110 *
#1845000
b10111 !
b10111 (
1$
#1850000
0$
b110111 #
b110111 '
b10110111 *
#1855000
b11000 !
b11000 (
1$
#1860000
0$
b111000 #
b111000 '
b10111000 *
#1865000
b11001 !
b11001 (
1$
#1870000
0$
b111001 #
b111001 '
b10111001 *
#1875000
b11010 !
b11010 (
1$
#1880000
0$
b111010 #
b111010 '
b10111010 *
#1885000
b11011 !
b11011 (
1$
#1890000
0$
b111011 #
b111011 '
b10111011 *
#1895000
b11100 !
b11100 (
1$
#1900000
0$
b111100 #
b111100 '
b10111100 *
#1905000
b11101 !
b11101 (
1$
#1910000
0$
b111101 #
b111101 '
b10111101 *
#1915000
b11110 !
b11110 (
1$
#1920000
0$
b111110 #
b111110 '
b10111110 *
#1925000
b11111 !
b11111 (
1$
#1930000
0$
b111111 #
b111111 '
b10111111 *
#1935000
b0 !
b0 (
1$
#1940000
0$
b0 #
b0 '
b11000000 *
#1945000
b1 !
b1 (
1$
#1950000
0$
b1 #
b1 '
b11000001 *
#1955000
b10 !
b10 (
1$
#1960000
0$
b10 #
b10 '
b11000010 *
#1965000
b11 !
b11 (
1$
#1970000
0$
b11 #
b11 '
b11000011 *
#1975000
b100 !
b100 (
1$
#1980000
0$
b100 #
b100 '
b11000100 *
#1985000
b101 !
b101 (
1$
#1990000
0$
b101 #
b101 '
b11000101 *
#1995000
b110 !
b110 (
1$
#2000000
0$
b110 #
b110 '
b11000110 *
#2005000
b111 !
b111 (
1$
#2010000
0$
b111 #
b111 '
b11000111 *
#2015000
b1000 !
b1000 (
1$
#2020000
0$
b1000 #
b1000 '
b11001000 *
#2025000
b1001 !
b1001 (
1$
#2030000
0$
b1001 #
b1001 '
b11001001 *
#2035000
b1010 !
b1010 (
1$
#2040000
0$
b1010 #
b1010 '
b11001010 *
#2045000
b1011 !
b1011 (
1$
#2050000
0$
b1011 #
b1011 '
b11001011 *
#2055000
b1100 !
b1100 (
1$
#2060000
0$
b1100 #
b1100 '
b11001100 *
#2065000
b1101 !
b1101 (
1$
#2070000
0$
b1101 #
b1101 '
b11001101 *
#2075000
b1110 !
b1110 (
1$
#2080000
0$
b1110 #
b1110 '
b11001110 *
#2085000
b1111 !
b1111 (
1$
#2090000
0$
b1111 #
b1111 '
b11001111 *
#2095000
b10000 !
b10000 (
1$
#2100000
0$
b10000 #
b10000 '
b11010000 *
#2105000
b10001 !
b10001 (
1$
#2110000
0$
b10001 #
b10001 '
b11010001 *
#2115000
b10010 !
b10010 (
1$
#2120000
0$
b10010 #
b10010 '
b11010010 *
#2125000
b10011 !
b10011 (
1$
#2130000
0$
b10011 #
b10011 '
b11010011 *
#2135000
b10100 !
b10100 (
1$
#2140000
0$
b10100 #
b10100 '
b11010100 *
#2145000
b10101 !
b10101 (
1$
#2150000
0$
b10101 #
b10101 '
b11010101 *
#2155000
b10110 !
b10110 (
1$
#2160000
0$
b10110 #
b10110 '
b11010110 *
#2165000
b10111 !
b10111 (
1$
#2170000
0$
b10111 #
b10111 '
b11010111 *
#2175000
b11000 !
b11000 (
1$
#2180000
0$
b11000 #
b11000 '
b11011000 *
#2185000
b11001 !
b11001 (
1$
#2190000
0$
b11001 #
b11001 '
b11011001 *
#2195000
b11010 !
b11010 (
1$
#2200000
0$
b11010 #
b11010 '
b11011010 *
#2205000
b11011 !
b11011 (
1$
#2210000
0$
b11011 #
b11011 '
b11011011 *
#2215000
b11100 !
b11100 (
1$
#2220000
0$
b11100 #
b11100 '
b11011100 *
#2225000
b11101 !
b11101 (
1$
#2230000
0$
b11101 #
b11101 '
b11011101 *
#2235000
b11110 !
b11110 (
1$
#2240000
0$
b11110 #
b11110 '
b11011110 *
#2245000
b11111 !
b11111 (
1$
#2250000
0$
b11111 #
b11111 '
b11011111 *
#2255000
b0 !
b0 (
1$
#2260000
0$
b100000 #
b100000 '
b11100000 *
#2265000
b1 !
b1 (
1$
#2270000
0$
b100001 #
b100001 '
b11100001 *
#2275000
b10 !
b10 (
1$
#2280000
0$
b100010 #
b100010 '
b11100010 *
#2285000
b11 !
b11 (
1$
#2290000
0$
b100011 #
b100011 '
b11100011 *
#2295000
b100 !
b100 (
1$
#2300000
0$
b100100 #
b100100 '
b11100100 *
#2305000
b101 !
b101 (
1$
#2310000
0$
b100101 #
b100101 '
b11100101 *
#2315000
b110 !
b110 (
1$
#2320000
0$
b100110 #
b100110 '
b11100110 *
#2325000
b111 !
b111 (
1$
#2330000
0$
b100111 #
b100111 '
b11100111 *
#2335000
b1000 !
b1000 (
1$
#2340000
0$
b101000 #
b101000 '
b11101000 *
#2345000
b1001 !
b1001 (
1$
#2350000
0$
b101001 #
b101001 '
b11101001 *
#2355000
b1010 !
b1010 (
1$
#2360000
0$
b101010 #
b101010 '
b11101010 *
#2365000
b1011 !
b1011 (
1$
#2370000
0$
b101011 #
b101011 '
b11101011 *
#2375000
b1100 !
b1100 (
1$
#2380000
0$
b101100 #
b101100 '
b11101100 *
#2385000
b1101 !
b1101 (
1$
#2390000
0$
b101101 #
b101101 '
b11101101 *
#2395000
b1110 !
b1110 (
1$
#2400000
0$
b101110 #
b101110 '
b11101110 *
#2405000
b1111 !
b1111 (
1$
#2410000
0$
b101111 #
b101111 '
b11101111 *
#2415000
b10000 !
b10000 (
1$
#2420000
0$
b110000 #
b110000 '
b11110000 *
#2425000
b10001 !
b10001 (
1$
#2430000
0$
b110001 #
b110001 '
b11110001 *
#2435000
b10010 !
b10010 (
1$
#2440000
0$
b110010 #
b110010 '
b11110010 *
#2445000
b10011 !
b10011 (
1$
#2450000
0$
b110011 #
b110011 '
b11110011 *
#2455000
b10100 !
b10100 (
1$
#2460000
0$
b110100 #
b110100 '
b11110100 *
#2465000
b10101 !
b10101 (
1$
#2470000
0$
b110101 #
b110101 '
b11110101 *
#2475000
b10110 !
b10110 (
1$
#2480000
0$
b110110 #
b110110 '
b11110110 *
#2485000
b10111 !
b10111 (
1$
#2490000
0$
b110111 #
b110111 '
b11110111 *
#2495000
b11000 !
b11000 (
1$
#2500000
0$
b111000 #
b111000 '
b11111000 *
#2505000
b11001 !
b11001 (
1$
#2510000
0$
b111001 #
b111001 '
b11111001 *
#2515000
b11010 !
b11010 (
1$
#2520000
0$
b111010 #
b111010 '
b11111010 *
#2525000
b11011 !
b11011 (
1$
#2530000
0$
b111011 #
b111011 '
b11111011 *
#2535000
b11100 !
b11100 (
1$
#2540000
0$
b111100 #
b111100 '
b11111100 *
#2545000
b11101 !
b11101 (
1$
#2550000
0$
b111101 #
b111101 '
b11111101 *
#2555000
b11110 !
b11110 (
1$
#2560000
0$
b111110 #
b111110 '
b11111110 *
#2565000
b11111 !
b11111 (
1$
#2570000
0$
b111111 #
b111111 '
b11111111 *
#2575000
b0 !
b0 (
1$
#2580000
0$
b0 #
b0 '
b1 "
b1 &
b1 )
b0 *
#2585000
1$
#2590000
0$
b1 #
b1 '
b1 *
#2595000
b1 !
b1 (
1$
#2600000
0$
b10 #
b10 '
b10 *
#2605000
b10 !
b10 (
1$
#2610000
0$
b11 #
b11 '
b11 *
#2615000
b11 !
b11 (
1$
#2620000
0$
b100 #
b100 '
b100 *
#2625000
b100 !
b100 (
1$
#2630000
0$
b101 #
b101 '
b101 *
#2635000
b101 !
b101 (
1$
#2640000
0$
b110 #
b110 '
b110 *
#2645000
b110 !
b110 (
1$
#2650000
0$
b111 #
b111 '
b111 *
#2655000
b111 !
b111 (
1$
#2660000
0$
b1000 #
b1000 '
b1000 *
#2665000
b1000 !
b1000 (
1$
#2670000
0$
b1001 #
b1001 '
b1001 *
#2675000
b1001 !
b1001 (
1$
#2680000
0$
b1010 #
b1010 '
b1010 *
#2685000
b1010 !
b1010 (
1$
#2690000
0$
b1011 #
b1011 '
b1011 *
#2695000
b1011 !
b1011 (
1$
#2700000
0$
b1100 #
b1100 '
b1100 *
#2705000
b1100 !
b1100 (
1$
#2710000
0$
b1101 #
b1101 '
b1101 *
#2715000
b1101 !
b1101 (
1$
#2720000
0$
b1110 #
b1110 '
b1110 *
#2725000
b1110 !
b1110 (
1$
#2730000
0$
b1111 #
b1111 '
b1111 *
#2735000
b1111 !
b1111 (
1$
#2740000
0$
b10000 #
b10000 '
b10000 *
#2745000
b10000 !
b10000 (
1$
#2750000
0$
b10001 #
b10001 '
b10001 *
#2755000
b10001 !
b10001 (
1$
#2760000
0$
b10010 #
b10010 '
b10010 *
#2765000
b10010 !
b10010 (
1$
#2770000
0$
b10011 #
b10011 '
b10011 *
#2775000
b10011 !
b10011 (
1$
#2780000
0$
b10100 #
b10100 '
b10100 *
#2785000
b10100 !
b10100 (
1$
#2790000
0$
b10101 #
b10101 '
b10101 *
#2795000
b10101 !
b10101 (
1$
#2800000
0$
b10110 #
b10110 '
b10110 *
#2805000
b10110 !
b10110 (
1$
#2810000
0$
b10111 #
b10111 '
b10111 *
#2815000
b10111 !
b10111 (
1$
#2820000
0$
b11000 #
b11000 '
b11000 *
#2825000
b11000 !
b11000 (
1$
#2830000
0$
b11001 #
b11001 '
b11001 *
#2835000
b11001 !
b11001 (
1$
#2840000
0$
b11010 #
b11010 '
b11010 *
#2845000
b11010 !
b11010 (
1$
#2850000
0$
b11011 #
b11011 '
b11011 *
#2855000
b11011 !
b11011 (
1$
#2860000
0$
b11100 #
b11100 '
b11100 *
#2865000
b11100 !
b11100 (
1$
#2870000
0$
b11101 #
b11101 '
b11101 *
#2875000
b11101 !
b11101 (
1$
#2880000
0$
b11110 #
b11110 '
b11110 *
#2885000
b11110 !
b11110 (
1$
#2890000
0$
b11111 #
b11111 '
b11111 *
#2895000
b11111 !
b11111 (
1$
#2900000
0$
b100000 #
b100000 '
b100000 *
#2905000
b0 !
b0 (
1$
#2910000
0$
b100001 #
b100001 '
b100001 *
#2915000
b1 !
b1 (
1$
#2920000
0$
b100010 #
b100010 '
b100010 *
#2925000
b10 !
b10 (
1$
#2930000
0$
b100011 #
b100011 '
b100011 *
#2935000
b11 !
b11 (
1$
#2940000
0$
b100100 #
b100100 '
b100100 *
#2945000
b100 !
b100 (
1$
#2950000
0$
b100101 #
b100101 '
b100101 *
#2955000
b101 !
b101 (
1$
#2960000
0$
b100110 #
b100110 '
b100110 *
#2965000
b110 !
b110 (
1$
#2970000
0$
b100111 #
b100111 '
b100111 *
#2975000
b111 !
b111 (
1$
#2980000
0$
b101000 #
b101000 '
b101000 *
#2985000
b1000 !
b1000 (
1$
#2990000
0$
b101001 #
b101001 '
b101001 *
#2995000
b1001 !
b1001 (
1$
#3000000
0$
b101010 #
b101010 '
b101010 *
#3005000
b1010 !
b1010 (
1$
#3010000
0$
b101011 #
b101011 '
b101011 *
#3015000
b1011 !
b1011 (
1$
#3020000
0$
b101100 #
b101100 '
b101100 *
#3025000
b1100 !
b1100 (
1$
#3030000
0$
b101101 #
b101101 '
b101101 *
#3035000
b1101 !
b1101 (
1$
#3040000
0$
b101110 #
b101110 '
b101110 *
#3045000
b1110 !
b1110 (
1$
#3050000
0$
b101111 #
b101111 '
b101111 *
#3055000
b1111 !
b1111 (
1$
