src/test/simple.sv
`timescale 1ns / 1ps
`default_nettype none

module simple (clk, reset, SW, LEDR);
input logic clk, reset;
input logic [1:0]SW;
output logic [2:0]LEDR ;
// State variables
//enum { none, got_one, got_two } ps, ns;
enum logic [2:0] {outer = 3'b101, right = 3'b001, middle = 3'b010, left= 3'b100} ps, ns;
// Next State logic
//always_comb begin
//case (ps)
//none: if (w) ns = got_one;
//else ns = none;
//got_one: if (w) ns = got_two;
//else ns = none;
//got_two: if (w) ns = got_two;
//else ns = none;
//endcase
//end
//
always_comb begin
case (ps)
	outer: if(~SW[0] & ~SW[1] & ~reset) ns = middle;
				else if(SW[0] & ~SW[1] & ~reset) ns = right;
				else if(~SW[0] & SW[1] & ~reset) ns = left;
				else ns = middle;
	right: if(~SW[0] & ~SW[1] & ~reset) ns = outer;
				else if(SW[0] & ~SW[1] & ~reset) ns = middle;
				else if(~SW[0] & SW[1] & ~reset) ns = left;
				else ns = outer;
	left: if(~SW[0] & ~SW[1] & ~reset) ns = middle;
				else if(SW[0] & ~SW[1] & ~reset) ns = right;
				else if(~SW[0] & SW[1] & ~reset) ns = middle;
				else ns = outer;
	middle: if(~SW[0] & ~SW[1] & ~reset) ns = outer;
				else if(SW[0] & ~SW[1] & ~reset) ns = left;
				else if(~SW[0] & SW[1] & ~reset ) ns = right;
				else ns = outer;
endcase
end
endmodule

// Output logic - could also be another always_comb block.

// DFFs
always_ff @(posedge clk) begin
if (reset) begin
//ps <= outer;
ps <= outer;
LEDR <= ps;
end
else begin
ps <= ns;
LEDR <= ps;
end
end


module simple_testbench();
logic clk, reset;
logic [1:0]SW;
logic [2:0]LEDR ;
simple dut (.*);
// Set up a simulated clock.
parameter CLOCK_PERIOD=100;
initial begin
 $dumpfile("simple.vcd"); //file to store value change dump (vcd)
        $dumpvars(0,simple_testbench); //store everything at the current level and below
clk <= 0;
forever #(CLOCK_PERIOD/2) clk <= ~clk; // Forever toggle the clock
end
// Set up the inputs to the design. Each line is a clock cycle.
initial begin
@(posedge clk);
reset <= 1; @(posedge clk); // Always reset FSMs at start // two clock cycles to check alternating test
@(posedge clk);
reset <= 0; @(posedge clk); // two clock cycles to check alternating test
@(posedge clk);
@(posedge clk);
@(posedge clk);
SW <= 2'b11;  @(posedge clk);
@(posedge clk);
@(posedge clk);
@(posedge clk);
SW <= 2'b01;  @(posedge clk);
@(posedge clk);
@(posedge clk);
@(posedge clk);
SW <= 2'b10; @(posedge clk);
@(posedge clk);
@(posedge clk);
@(posedge clk);
SW <= 2'b00; @(posedge clk);
@(posedge clk);
@(posedge clk);
@(posedge clk);
$stop; // End the simulation.
end
endmodule

src/test/simple.vcd
$date
	Tue Aug 27 19:33:36 2024
$end
$version
	Icarus Verilog
$end
$timescale
	1ps
$end
$scope module simple_testbench $end
$var wire 3 ! LEDR [2:0] $end
$var parameter 32 " CLOCK_PERIOD $end
$var reg 2 # SW [1:0] $end
$var reg 1 $ clk $end
$var reg 1 % reset $end
$scope module dut $end
$var wire 2 & SW [1:0] $end
$var wire 1 $ clk $end
$var wire 1 % reset $end
$var reg 3 ' LEDR [2:0] $end
$var reg 3 ( ns [2:0] $end
$var reg 3 ) ps [2:0] $end
$upscope $end
$upscope $end
$enddefinitions $end
$comment Show the parameter values. $end
$dumpall
b1100100 "
$end
#0
$dumpvars
bx )
bx (
bx '
bx &
x%
0$
bx #
bx !
$end
#50000
1%
1$
#100000
0$
#150000
b10 (
b101 )
1$
#200000
0$
#250000
b101 !
b101 '
0%
1$
#300000
0$
#350000
b101 (
b10 )
1$
#400000
0$
#450000
b10 (
b10 !
b10 '
b101 )
1$
#500000
0$
#550000
b101 (
b101 !
b101 '
b10 )
1$
#600000
0$
#650000
b10 (
b10 !
b10 '
b101 )
b11 #
b11 &
1$
#700000
0$
#750000
b101 (
b101 !
b101 '
b10 )
1$
#800000
0$
#850000
b10 (
b10 !
b10 '
b101 )
1$
#900000
0$
#950000
b101 (
b101 !
b101 '
b10 )
1$
#1000000
0$
#1050000
b1 (
b10 !
b10 '
b101 )
b1 #
b1 &
1$
#1100000
0$
#1150000
b10 (
b101 !
b101 '
b1 )
1$
#1200000
0$
#1250000
b100 (
b1 !
b1 '
b10 )
1$
#1300000
0$
#1350000
b1 (
b10 !
b10 '
b100 )
1$
#1400000
0$
#1450000
b100 (
b100 !
b100 '
b1 )
b10 #
b10 &
1$
#1500000
0$
#1550000
b10 (
b1 !
b1 '
b100 )
1$
#1600000
0$
#1650000
b1 (
b100 !
b100 '
b10 )
1$
#1700000
0$
#1750000
b100 (
b10 !
b10 '
b1 )
1$
#1800000
0$
#1850000
b10 (
b1 !
b1 '
b100 )
b0 #
b0 &
1$
#1900000
0$
#1950000
b101 (
b100 !
b100 '
b10 )
1$
#2000000
0$
#2050000
b10 (
b10 !
b10 '
b101 )
1$
#2100000
0$
#2150000
b101 (
b101 !
b101 '
b10 )
1$
#2200000
0$
#2250000
b10 (
b10 !
b10 '
b101 )
1$
#2300000
0$
#2350000
b101 (
b101 !
b101 '
b10 )
1$
#2400000
0$
#2450000
b10 (
b10 !
b10 '
b101 )
1$
#2500000
0$
#2550000
b101 (
b101 !
b101 '
b10 )
1$
#2600000
0$
#2650000
b10 (
b10 !
b10 '
b101 )
1$
#2700000
0$
#2750000
b101 (
b101 !
b101 '
b10 )
1$
#2800000
0$
#2850000
b10 (
b10 !
b10 '
b101 )
1$
#2900000
0$
#2950000
b101 (
b101 !
b101 '
b10 )
1$
#3000000
0$
#3050000
b10 (
b10 !
b10 '
b101 )
1$
#3100000
0$
#3150000
b101 (
b101 !
b101 '
b10 )
1$
#3200000
0$
#3250000
b10 (
b10 !
b10 '
b101 )
1$
#3300000
0$
#3350000
b101 (
b101 !
b101 '
b10 )
1$
#3400000
0$
#3450000
b10 (
b10 !
b10 '
b101 )
1$
#3500000
0$
#3550000
b101 (
b101 !
b101 '
b10 )
1$
#3600000
0$
#3650000
b10 (
b10 !
b10 '
b101 )
1$
#3700000
0$
#3750000
b101 (
b101 !
b101 '
b10 )
1$
#3800000
0$
#3850000
b10 (
b10 !
b10 '
b101 )
1$
#3900000
0$
#3950000
b101 (
b101 !
b101 '
b10 )
1$
#4000000
0$
#4050000
b10 (
b10 !
b10 '
b101 )
1$
#4100000
0$
#4150000
b101 (
b101 !
b101 '
b10 )
1$
#4200000
0$
#4250000
b10 (
b10 !
b10 '
b101 )
1$
#4300000
0$
#4350000
b101 (
b101 !
b101 '
b10 )
1$
#4400000
0$
#4450000
b10 (
b10 !
b10 '
b101 )
1$
#4500000
0$
#4550000
b101 (
b101 !
b101 '
b10 )
1$
#4600000
0$
#4650000
b10 (
b10 !
b10 '
b101 )
1$
#4700000
0$
#4750000
b101 (
b101 !
b101 '
b10 )
1$
#4800000
0$
#4850000
b10 (
b10 !
b10 '
b101 )
1$
#4900000
0$
#4950000
b101 (
b101 !
b101 '
b10 )
1$
#5000000
0$
#5050000
b10 (
b10 !
b10 '
b101 )
1$
#5100000
0$
#5150000
b101 (
b101 !
b101 '
b10 )
1$
#5200000
0$
#5250000
b10 (
b10 !
b10 '
b101 )
1$
#5300000
0$
#5350000
b101 (
b101 !
b101 '
b10 )
1$
#5400000
0$
#5450000
b10 (
b10 !
b10 '
b101 )
1$
#5500000
0$
#5550000
b101 (
b101 !
b101 '
b10 )
1$
#5600000
0$
#5650000
b10 (
b10 !
b10 '
b101 )
1$
#5700000
0$
#5750000
b101 (
b101 !
b101 '
b10 )
1$
#5800000
0$
#5850000
b10 (
b10 !
b10 '
b101 )
1$
#5900000
0$
#5950000
b101 (
b101 !
b101 '
b10 )
1$
#6000000
0$
#6050000
b10 (
b10 !
b10 '
b101 )
1$
#6100000
0$
#6150000
b101 (
b101 !
b101 '
b10 )
1$
#6200000
0$
#6250000
b10 (
b10 !
b10 '
b101 )
1$
#6300000
0$
#6350000
b101 (
b101 !
b101 '
b10 )
1$
#6400000
0$
#6450000
b10 (
b10 !
b10 '
b101 )
1$
#6500000
0$
#6550000
b101 (
b101 !
b101 '
b10 )
1$
#6600000
0$
#6650000
b10 (
b10 !
b10 '
b101 )
1$
#6700000
0$
#6750000
b101 (
b101 !
b101 '
b10 )
1$
#6800000
0$
#6850000
b10 (
b10 !
b10 '
b101 )
1$
#6900000
0$
#6950000
b101 (
b101 !
b101 '
b10 )
1$
#7000000
0$
#7050000
b10 (
b10 !
b10 '
b101 )
1$
#7100000
0$
#7150000
b101 (
b101 !
b101 '
b10 )
1$
#7200000
0$
#7250000
b10 (
b10 !
b10 '
b101 )
1$
#7300000
0$
#7350000
b101 (
b101 !
b101 '
b10 )
1$
#7400000
0$
#7450000
b10 (
b10 !
b10 '
b101 )
1$
#7500000
0$
#7550000
b101 (
b101 !
b101 '
b10 )
1$
#7600000
0$
#7650000
b10 (
b10 !
b10 '
b101 )
1$
#7700000
0$
#7750000
b101 (
b101 !
b101 '
b10 )
1$
#7800000
0$
#7850000
b10 (
b10 !
b10 '
b101 )
1$
#7900000
0$
#7950000
b101 (
b101 !
b101 '
b10 )
1$
#8000000
0$
#8050000
b10 (
b10 !
b10 '
b101 )
1$
#8100000
0$
#8150000
b101 (
b101 !
b101 '
b10 )
1$
#8200000
0$
#8250000
b10 (
b10 !
b10 '
b101 )
1$
#8300000
0$
#8350000
b101 (
b101 !
b101 '
b10 )
1$
#8400000
0$
#8450000
b10 (
b10 !
b10 '
b101 )
1$
#8500000
0$
#8550000
b101 (
b101 !
b101 '
b10 )
1$
#8600000
0$
#8650000
b10 (
b10 !
b10 '
b101 )
1$
#8700000
0$
#8750000
b101 (
b101 !
b101 '
b10 )
1$
#8800000
0$
#8850000
b10 (
b10 !
b10 '
b101 )
1$
#8900000
0$
#8950000
b101 (
b101 !
b101 '
b10 )
1$
#9000000
0$
#9050000
b10 (
b10 !
b10 '
b101 )
1$
#9100000
0$
#9150000
b101 (
b101 !
b101 '
b10 )
1$
#9200000
0$
#9250000
b10 (
b10 !
b10 '
b101 )
1$
#9300000
0$
#9350000
b101 (
b101 !
b101 '
b10 )
1$
#9400000
0$
#9450000
b10 (
b10 !
b10 '
b101 )
1$
#9500000
0$
#9550000
b101 (
b101 !
b101 '
b10 )
1$
#9600000
0$
#9650000
b10 (
b10 !
b10 '
b101 )
1$
#9700000
0$
#9750000
b101 (
b101 !
b101 '
b10 )
1$
#9800000
0$
#9850000
b10 (
b10 !
b10 '
b101 )
1$
#9900000
0$
#9950000
b101 (
b101 !
b101 '
b10 )
1$
#10000000
0$
#10050000
b10 (
b10 !
b10 '
b101 )
1$
#10100000
0$
#10150000
b101 (
b101 !
b101 '
b10 )
1$
#10200000
0$
#10250000
b10 (
b10 !
b10 '
b101 )
1$
#10300000
0$
#10350000
b101 (
b101 !
b101 '
b10 )
1$
#10400000
0$
#10450000
b10 (
b10 !
b10 '
b101 )
1$
#10500000
0$
#10550000
b101 (
b101 !
b101 '
b10 )
1$
#10600000
0$
#10650000
b10 (
b10 !
b10 '
b101 )
1$
#10700000
0$
#10750000
b101 (
b101 !
b101 '
b10 )
1$
#10800000
0$
#10850000
b10 (
b10 !
b10 '
b101 )
1$
#10900000
0$
#10950000
b101 (
b101 !
b101 '
b10 )
1$
#11000000
0$
#11050000
b10 (
b10 !
b10 '
b101 )
1$
#11100000
0$
#11150000
b101 (
b101 !
b101 '
b10 )
1$
#11200000
0$
#11250000
b10 (
b10 !
b10 '
b101 )
1$
#11300000
0$
#11350000
b101 (
b101 !
b101 '
b10 )
1$
#11400000
0$
#11450000
b10 (
b10 !
b10 '
b101 )
1$
#11500000
0$
#11550000
b101 (
b101 !
b101 '
b10 )
1$
#11600000
0$
#11650000
b10 (
b10 !
b10 '
b101 )
1$
#11700000
0$
#11750000
b101 (
b101 !
b101 '
b10 )
1$
#11800000
0$
#11850000
b10 (
b10 !
b10 '
b101 )
1$
#11900000
0$
#11950000
b101 (
b101 !
b101 '
b10 )
1$
#12000000
0$
#12050000
b10 (
b10 !
b10 '
b101 )
1$
#12100000
0$
#12150000
b101 (
b101 !
b101 '
b10 )
1$
#12200000
0$
#12250000
b10 (
b10 !
b10 '
b101 )
1$
#12300000
0$
#12350000
b101 (
b101 !
b101 '
b10 )
1$
#12400000
0$
#12450000
b10 (
b10 !
b10 '
b101 )
1$
#12500000
0$
#12550000
b101 (
b101 !
b101 '
b10 )
1$
#12600000
0$
#12650000
b10 (
b10 !
b10 '
b101 )
1$
#12700000
0$
#12750000
b101 (
b101 !
b101 '
b10 )
1$
#12800000
0$
#12850000
b10 (
b10 !
b10 '
b101 )
1$
#12900000
0$
#12950000
b101 (
b101 !
b101 '
b10 )
1$
#13000000
0$
#13050000
b10 (
b10 !
b10 '
b101 )
1$
#13100000
0$
#13150000
b101 (
b101 !
b101 '
b10 )
1$
#13200000
0$
#13250000
b10 (
b10 !
b10 '
b101 )
1$
#13300000
0$
#13350000
b101 (
b101 !
b101 '
b10 )
1$
#13400000
0$
#13450000
b10 (
b10 !
b10 '
b101 )
1$
#13500000
0$
#13550000
b101 (
b101 !
b101 '
b10 )
1$
#13600000
0$
#13650000
b10 (
b10 !
b10 '
b101 )
1$
#13700000
0$
#13750000
b101 (
b101 !
b101 '
b10 )
1$
#13800000
0$
#13850000
b10 (
b10 !
b10 '
b101 )
1$
#13900000
0$
#13950000
b101 (
b101 !
b101 '
b10 )
1$
#14000000
0$
#14050000
b10 (
b10 !
b10 '
b101 )
1$
#14100000
0$
#14150000
b101 (
b101 !
b101 '
b10 )
1$
#14200000
0$
#14250000
b10 (
b10 !
b10 '
b101 )
1$
#14300000
0$
#14350000
b101 (
b101 !
b101 '
b10 )
1$
#14400000
0$
#14450000
b10 (
b10 !
b10 '
b101 )
1$
#14500000
0$
#14550000
b101 (
b101 !
b101 '
b10 )
1$
#14600000
0$
#14650000
b10 (
b10 !
b10 '
b101 )
1$
#14700000
0$
#14750000
b101 (
b101 !
b101 '
b10 )
1$
#14800000
0$
#14850000
b10 (
b10 !
b10 '
b101 )
1$
#14900000
0$
#14950000
b101 (
b101 !
b101 '
b10 )
1$
#15000000
0$
#15050000
b10 (
b10 !
b10 '
b101 )
1$
#15100000
0$
#15150000
b101 (
b101 !
b101 '
b10 )
1$
#15200000
0$
#15250000
b10 (
b10 !
b10 '
b101 )
1$
#15300000
0$
#15350000
b101 (
b101 !
b101 '
b10 )
1$
#15400000
0$
#15450000
b10 (
b10 !
b10 '
b101 )
1$
#15500000
0$
#15550000
b101 (
b101 !
b101 '
b10 )
1$
#15600000
0$
#15650000
b10 (
b10 !
b10 '
b101 )
1$
#15700000
0$
#15750000
b101 (
b101 !
b101 '
b10 )
1$
#15800000
0$
#15850000
b10 (
b10 !
b10 '
b101 )
1$
#15900000
0$
#15950000
b101 (
b101 !
b101 '
b10 )
1$
#16000000
0$
#16050000
b10 (
b10 !
b10 '
b101 )
1$
#16100000
0$
#16150000
b101 (
b101 !
b101 '
b10 )
1$
#16200000
0$
#16250000
b10 (
b10 !
b10 '
b101 )
1$
#16300000
0$
#16350000
b101 (
b101 !
b101 '
b10 )
1$
#16400000
0$
#16450000
b10 (
b10 !
b10 '
b101 )
1$
#16500000
0$
#16550000
b101 (
b101 !
b101 '
b10 )
1$
#16600000
0$
#16650000
b10 (
b10 !
b10 '
b101 )
1$
#16700000
0$
#16750000
b101 (
b101 !
b101 '
b10 )
1$
#16800000
0$
#16850000
b10 (
b10 !
b10 '
b101 )
1$
#16900000
0$
#16950000
b101 (
b101 !
b101 '
b10 )
1$
#17000000
0$
#17050000
b10 (
b10 !
b10 '
b101 )
1$
#17100000
0$
#17150000
b101 (
b101 !
b101 '
b10 )
1$
#17200000
0$
#17250000
b10 (
b10 !
b10 '
b101 )
1$
#17300000
0$
#17350000
b101 (
b101 !
b101 '
b10 )
1$
#17400000
0$
#17450000
b10 (
b10 !
b10 '
b101 )
1$
#17500000
0$
#17550000
b101 (
b101 !
b101 '
b10 )
1$
#17600000
0$
#17650000
b10 (
b10 !
b10 '
b101 )
1$
#17700000
0$
#17750000
b101 (
b101 !
b101 '
b10 )
1$
#17800000
0$
#17850000
b10 (
b10 !
b10 '
b101 )
1$
#17900000
0$
#17950000
b101 (
b101 !
b101 '
b10 )
1$
#18000000
0$
#18050000
b10 (
b10 !
b10 '
b101 )
1$
#18100000
0$
#18150000
b101 (
b101 !
b101 '
b10 )
1$
#18200000
0$
#18250000
b10 (
b10 !
b10 '
b101 )
1$
#18300000
0$
#18350000
b101 (
b101 !
b101 '
b10 )
1$
#18400000
0$
#18450000
b10 (
b10 !
b10 '
b101 )
1$
#18500000
0$
#18550000
b101 (
b101 !
b101 '
b10 )
1$
#18600000
0$
#18650000
b10 (
b10 !
b10 '
b101 )
1$
#18700000
0$
#18750000
b101 (
b101 !
b101 '
b10 )
1$
#18800000
0$
#18850000
b10 (
b10 !
b10 '
b101 )
1$
#18900000
0$
#18950000
b101 (
b101 !
b101 '
b10 )
1$
#19000000
0$
#19050000
b10 (
b10 !
b10 '
b101 )
1$
#19100000
0$
#19150000
b101 (
b101 !
b101 '
b10 )
1$
#19200000
0$
#19250000
b10 (
b10 !
b10 '
b101 )
1$
#19300000
0$
#19350000
b101 (
b101 !
b101 '
b10 )
1$
#19400000
0$
#19450000
b10 (
b10 !
b10 '
b101 )
1$
#19500000
0$
#19550000
b101 (
b101 !
b101 '
b10 )
1$
#19600000
0$
#19650000
b10 (
b10 !
b10 '
b101 )
1$
#19700000
0$
#19750000
b101 (
b101 !
b101 '
b10 )
1$
#19800000
0$
#19850000
b10 (
b10 !
b10 '
b101 )
1$
#19900000
0$
#19950000
b101 (
b101 !
b101 '
b10 )
1$
#20000000
0$
#20050000
b10 (
b10 !
b10 '
b101 )
1$
#20100000
0$
#20150000
b101 (
b101 !
b101 '
b10 )
1$
#20200000
0$
#20250000
b10 (
b10 !
b10 '
b101 )
1$
#20300000
0$
#20350000
b101 (
b101 !
b101 '
b10 )
1$
#20400000
0$
#20450000
b10 (
b10 !
b10 '
b101 )
1$
#20500000
0$
#20550000
b101 (
b101 !
b101 '
b10 )
1$
#20600000
0$
#20650000
b10 (
b10 !
b10 '
b101 )
1$
#20700000
0$
#20750000
b101 (
b101 !
b101 '
b10 )
1$
#20800000
0$
#20850000
b10 (
b10 !
b10 '
b101 )
1$
#20900000
0$
#20950000
b101 (
b101 !
b101 '
b10 )
1$
#21000000
0$
#21050000
b10 (
b10 !
b10 '
b101 )
1$
#21100000
0$
#21150000
b101 (
b101 !
b101 '
b10 )
1$
#21200000
0$
#21250000
b10 (
b10 !
b10 '
b101 )
1$
#21300000
0$
#21350000
b101 (
b101 !
b101 '
b10 )
1$
#21400000
0$
#21450000
b10 (
b10 !
b10 '
b101 )
1$
#21500000
0$
#21550000
b101 (
b101 !
b101 '
b10 )
1$
#21600000
0$
#21650000
b10 (
b10 !
b10 '
b101 )
1$
#21700000
0$
#21750000
b101 (
b101 !
b101 '
b10 )
1$
#21800000
0$
#21850000
b10 (
b10 !
b10 '
b101 )
1$
#21900000
0$
#21950000
b101 (
b101 !
b101 '
b10 )
1$
#22000000
0$
#22050000
b10 (
b10 !
b10 '
b101 )
1$
#22100000
0$
#22150000
b101 (
b101 !
b101 '
b10 )
1$
#22200000
0$
#22250000
b10 (
b10 !
b10 '
b101 )
1$
#22300000
0$
#22350000
b101 (
b101 !
b101 '
b10 )
1$
#22400000
0$
#22450000
b10 (
b10 !
b10 '
b101 )
1$
#22500000
0$
#22550000
b101 (
b101 !
b101 '
b10 )
1$
#22600000
0$
#22650000
b10 (
b10 !
b10 '
b101 )
1$
#22700000
0$
#22750000
b101 (
b101 !
b101 '
b10 )
1$
#22800000
0$
#22850000
b10 (
b10 !
b10 '
b101 )
1$
#22900000
0$
#22950000
b101 (
b101 !
b101 '
b10 )
1$
#23000000
0$
#23050000
b10 (
b10 !
b10 '
b101 )
1$
#23100000
0$
#23150000
b101 (
b101 !
b101 '
b10 )
1$
#23200000
0$
#23250000
b10 (
b10 !
b10 '
b101 )
1$
#23300000
0$
#23350000
b101 (
b101 !
b101 '
b10 )
1$
#23400000
0$
#23450000
b10 (
b10 !
b10 '
b101 )
1$
#23500000
0$
#23550000
b101 (
b101 !
b101 '
b10 )
1$
#23600000
0$
#23650000
b10 (
b10 !
b10 '
b101 )
1$
#23700000
0$
#23750000
b101 (
b101 !
b101 '
b10 )
1$
#23800000
0$
#23850000
b10 (
b10 !
b10 '
b101 )
1$
#23900000
0$
#23950000
b101 (
b101 !
b101 '
b10 )
1$
#24000000
0$
#24050000
b10 (
b10 !
b10 '
b101 )
1$
#24100000
0$
#24150000
b101 (
b101 !
b101 '
b10 )
1$
#24200000
0$
#24250000
b10 (
b10 !
b10 '
b101 )
1$
#24300000
0$
#24350000
b101 (
b101 !
b101 '
b10 )
1$
#24400000
0$
#24450000
b10 (
b10 !
b10 '
b101 )
1$
#24500000
0$
#24550000
b101 (
b101 !
b101 '
b10 )
1$
#24600000
0$
#24650000
b10 (
b10 !
b10 '
b101 )
1$
#24700000
0$
#24750000
b101 (
b101 !
b101 '
b10 )
1$
#24800000
0$
#24850000
b10 (
b10 !
b10 '
b101 )
1$
#24900000
0$
#24950000
b101 (
b101 !
b101 '
b10 )
1$
#25000000
0$
#25050000
b10 (
b10 !
b10 '
b101 )
1$
#25100000
0$
#25150000
b101 (
b101 !
b101 '
b10 )
1$
#25200000
0$
#25250000
b10 (
b10 !
b10 '
b101 )
1$
#25300000
0$
#25350000
b101 (
b101 !
b101 '
b10 )
1$
#25400000
0$
#25450000
b10 (
b10 !
b10 '
b101 )
1$
#25500000
0$
#25550000
b101 (
b101 !
b101 '
b10 )
1$
#25600000
0$
#25650000
b10 (
b10 !
b10 '
b101 )
1$
#25700000
0$
#25750000
b101 (
b101 !
b101 '
b10 )
1$
#25800000
0$
#25850000
b10 (
b10 !
b10 '
b101 )
1$
#25900000
0$
#25950000
b101 (
b101 !
b101 '
b10 )
1$
#26000000
0$
#26050000
b10 (
b10 !
b10 '
b101 )
1$
#26100000
0$
#26150000
b101 (
b101 !
b101 '
b10 )
1$
#26200000
0$
#26250000
b10 (
b10 !
b10 '
b101 )
1$
#26300000
0$
#26350000
b101 (
b101 !
b101 '
b10 )
1$
#26400000
0$
#26450000
b10 (
b10 !
b10 '
b101 )
1$
#26500000
0$
#26550000
b101 (
b101 !
b101 '
b10 )
1$
#26600000
0$
#26650000
b10 (
b10 !
b10 '
b101 )
1$
#26700000
0$
#26750000
b101 (
b101 !
b101 '
b10 )
1$
#26800000
0$
#26850000
b10 (
b10 !
b10 '
b101 )
1$
#26900000
0$
#26950000
b101 (
b101 !
b101 '
b10 )
1$
#27000000
0$
#27050000
b10 (
b10 !
b10 '
b101 )
1$
#27100000
0$
#27150000
b101 (
b101 !
b101 '
b10 )
1$
#27200000
0$
#27250000
b10 (
b10 !
b10 '
b101 )
1$
#27300000
0$
#27350000
b101 (
b101 !
b101 '
b10 )
1$
#27400000
0$
#27450000
b10 (
b10 !
b10 '
b101 )
1$
#27500000
0$
#27550000
b101 (
b101 !
b101 '
b10 )
1$
#27600000
0$
#27650000
b10 (
b10 !
b10 '
b101 )
1$
#27700000
0$
#27750000
b101 (
b101 !
b101 '
b10 )
1$
#27800000
0$
#27850000
b10 (
b10 !
b10 '
b101 )
1$
#27900000
0$
#27950000
b101 (
b101 !
b101 '
b10 )
1$
#28000000
0$
#28050000
b10 (
b10 !
b10 '
b101 )
1$
#28100000
0$
#28150000
b101 (
b101 !
b101 '
b10 )
1$
#28200000
0$
#28250000
b10 (
b10 !
b10 '
b101 )
1$
#28300000
0$
#28350000
b101 (
b101 !
b101 '
b10 )
1$
#28400000
0$
#28450000
b10 (
b10 !
b10 '
b101 )
1$
#28500000
0$
#28550000
b101 (
b101 !
b101 '
b10 )
1$
#28600000
0$
#28650000
b10 (
b10 !
b10 '
b101 )
1$
#28700000
0$
#28750000
b101 (
b101 !
b101 '
b10 )
1$
#28800000
0$
#28850000
b10 (
b10 !
b10 '
b101 )
1$
#28900000
0$
#28950000
b101 (
b101 !
b101 '
b10 )
1$
#29000000
0$
#29050000
b10 (
b10 !
b10 '
b101 )
1$
#29100000
0$
#29150000
b101 (
b101 !
b101 '
b10 )
1$
#29200000
0$
#29250000
b10 (
b10 !
b10 '
b101 )
1$
#29300000
0$
#29350000
b101 (
b101 !
b101 '
b10 )
1$
#29400000
0$
#29450000
b10 (
b10 !
b10 '
b101 )
1$
#29500000
0$
#29550000
b101 (
b101 !
b101 '
b10 )
1$
#29600000
0$
#29650000
b10 (
b10 !
b10 '
b101 )
1$
#29700000
0$
#29750000
b101 (
b101 !
b101 '
b10 )
1$
#29800000
0$
#29850000
b10 (
b10 !
b10 '
b101 )
1$
#29900000
0$
#29950000
b101 (
b101 !
b101 '
b10 )
1$
#30000000
0$
#30050000
b10 (
b10 !
b10 '
b101 )
1$
#30100000
0$
#30150000
b101 (
b101 !
b101 '
b10 )
1$
#30200000
0$
#30250000
b10 (
b10 !
b10 '
b101 )
1$
#30300000
0$
#30350000
b101 (
b101 !
b101 '
b10 )
1$
#30400000
0$
#30450000
b10 (
b10 !
b10 '
b101 )
1$
#30500000
0$
#30550000
b101 (
b101 !
b101 '
b10 )
1$
#30600000
0$
#30650000
b10 (
b10 !
b10 '
b101 )
1$
#30700000
0$
#30750000
b101 (
b101 !
b101 '
b10 )
1$
#30800000
0$
#30850000
b10 (
b10 !
b10 '
b101 )
1$
#30900000
0$
#30950000
b101 (
b101 !
b101 '
b10 )
1$
#31000000
0$
#31050000
b10 (
b10 !
b10 '
b101 )
1$
#31100000
0$
#31150000
b101 (
b101 !
b101 '
b10 )
1$
#31200000
0$
#31250000
b10 (
b10 !
b10 '
b101 )
1$
#31300000
0$
#31350000
b101 (
b101 !
b101 '
b10 )
1$
#31400000
0$
#31450000
b10 (
b10 !
b10 '
b101 )
1$
#31500000
0$
#31550000
b101 (
b101 !
b101 '
b10 )
1$
#31600000
0$
#31650000
b10 (
b10 !
b10 '
b101 )
1$
#31700000
0$
#31750000
b101 (
b101 !
b101 '
b10 )
1$
#31800000
0$
#31850000
b10 (
b10 !
b10 '
b101 )
1$
#31900000
0$
#31950000
b101 (
b101 !
b101 '
b10 )
1$
#32000000
0$
#32050000
b10 (
b10 !
b10 '
b101 )
1$
#32100000
0$
#32150000
b101 (
b101 !
b101 '
b10 )
1$
#32200000
0$
#32250000
b10 (
b10 !
b10 '
b101 )
1$
#32300000
0$
#32350000
b101 (
b101 !
b101 '
b10 )
1$
#32400000
0$
#32450000
b10 (
b10 !
b10 '
b101 )
1$
#32500000
0$
#32550000
b101 (
b101 !
b101 '
b10 )
1$
#32600000
0$
#32650000
b10 (
b10 !
b10 '
b101 )
1$
#32700000
0$
#32750000
b101 (
b101 !
b101 '
b10 )
1$
#32800000
0$
#32850000
b10 (
b10 !
b10 '
b101 )
1$
#32900000
0$
#32950000
b101 (
b101 !
b101 '
b10 )
1$
#33000000
0$
#33050000
b10 (
b10 !
b10 '
b101 )
1$
#33100000
0$
#33150000
b101 (
b101 !
b101 '
b10 )
1$
#33200000
0$
#33250000
b10 (
b10 !
b10 '
b101 )
1$
#33300000
0$
#33350000
b101 (
b101 !
b101 '
b10 )
1$
#33400000
0$
#33450000
b10 (
b10 !
b10 '
b101 )
1$
#33500000
0$
#33550000
b101 (
b101 !
b101 '
b10 )
1$
#33600000
0$
#33650000
b10 (
b10 !
b10 '
b101 )
1$
#33700000
0$
#33750000
b101 (
b101 !
b101 '
b10 )
1$
#33800000
0$
#33850000
b10 (
b10 !
b10 '
b101 )
1$
#33900000
0$
#33950000
b101 (
b101 !
b101 '
b10 )
1$
#34000000
0$
#34050000
b10 (
b10 !
b10 '
b101 )
1$
#34100000
0$
#34150000
b101 (
b101 !
b101 '
b10 )
1$
#34200000
0$
#34250000
b10 (
b10 !
b10 '
b101 )
1$
#34300000
0$
#34350000
b101 (
b101 !
b101 '
b10 )
1$
#34400000
0$
#34450000
b10 (
b10 !
b10 '
b101 )
1$
#34500000
0$
#34550000
b101 (
b101 !
b101 '
b10 )
1$
#34600000
0$
#34650000
b10 (
b10 !
b10 '
b101 )
1$
#34700000
0$
#34750000
b101 (
b101 !
b101 '
b10 )
1$
#34800000
0$
#34850000
b10 (
b10 !
b10 '
b101 )
1$
#34900000
0$
#34950000
b101 (
b101 !
b101 '
b10 )
1$
#35000000
0$
#35050000
b10 (
b10 !
b10 '
b101 )
1$
#35100000
0$
#35150000
b101 (
b101 !
b101 '
b10 )
1$
#35200000
0$
#35250000
b10 (
b10 !
b10 '
b101 )
1$
#35300000
0$
#35350000
b101 (
b101 !
b101 '
b10 )
1$
#35400000
0$
#35450000
b10 (
b10 !
b10 '
b101 )
1$
#35500000
0$
#35550000
b101 (
b101 !
b101 '
b10 )
1$
#35600000
0$
#35650000
b10 (
b10 !
b10 '
b101 )
1$
#35700000
0$
#35750000
b101 (
b101 !
b101 '
b10 )
1$
#35800000
0$
#35850000
b10 (
b10 !
b10 '
b101 )
1$
#35900000
0$
#35950000
b101 (
b101 !
b101 '
b10 )
1$
#36000000
0$
#36050000
b10 (
b10 !
b10 '
b101 )
1$
#36100000
0$
#36150000
b101 (
b101 !
b101 '
b10 )
1$
#36200000
0$
#36250000
b10 (
b10 !
b10 '
b101 )
1$
#36300000
0$
#36350000
b101 (
b101 !
b101 '
b10 )
1$
#36400000
0$
#36450000
b10 (
b10 !
b10 '
b101 )
1$
#36500000
0$
#36550000
b101 (
b101 !
b101 '
b10 )
1$
#36600000
0$
#36650000
b10 (
b10 !
b10 '
b101 )
1$
#36700000
0$
#36750000
b101 (
b101 !
b101 '
b10 )
1$
#36800000
0$
#36850000
b10 (
b10 !
b10 '
b101 )
1$
#36900000
0$
#36950000
b101 (
b101 !
b101 '
b10 )
1$
