src/test/simple.sv
`timescale 1ns / 1ps
`default_nettype none

module simple (clk, reset, SW, LEDR);
input logic clk, reset;
input logic [1:0]SW;
output logic [2:0]LEDR ;
// State variables
//enum { none, got_one, got_two } ps, ns;
enum logic [2:0] {outer = 3'b101, right = 3'b001, middle = 3'b010, left= 3'b100} ps, ns;
// Next State logic
//always_comb begin
//case (ps)
//none: if (w) ns = got_one;
//else ns = none;
//got_one: if (w) ns = got_two;
//else ns = none;
//got_two: if (w) ns = got_two;
//else ns = none;
//endcase
//end
//
always_comb begin
case (ps)
	outer: if(~SW[0] & ~SW[1] & ~reset) ns = middle;
				else if(SW[0] & ~SW[1] & ~reset) ns = right;
				else if(~SW[0] & SW[1] & ~reset) ns = left;
				else ns = middle;
	right: if(~SW[0] & ~SW[1] & ~reset) ns = outer;
				else if(SW[0] & ~SW[1] & ~reset) ns = middle;
				else if(~SW[0] & SW[1] & ~reset) ns = left;
				else ns = outer;
	left: if(~SW[0] & ~SW[1] & ~reset) ns = middle;
				else if(SW[0] & ~SW[1] & ~reset) ns = right;
				else if(~SW[0] & SW[1] & ~reset) ns = middle;
				else ns = outer;
	middle: if(~SW[0] & ~SW[1] & ~reset) ns = outer;
				else if(SW[0] & ~SW[1] & ~reset) ns = left;
				else if(~SW[0] & SW[1] & ~reset ) ns = right;
				else ns = outer;
endcase
end

// Output logic - could also be another always_comb block.

// DFFs
always_ff @(posedge clk) begin
if (reset) begin
//ps <= outer;
ps <= outer;
LEDR <= ps;
end
else begin
ps <= ns;
LEDR <= ps;
end
end
endmodule

module simple_testbench();
logic clk, reset;
logic [1:0]SW;
logic [2:0]LEDR ;
simple dut (.*);
// Set up a simulated clock.
parameter CLOCK_PERIOD=100;
initial begin
 $dumpfile("simple.vcd"); //file to store value change dump (vcd)
        $dumpvars(0,simple_testbench); //store everything at the current level and below
clk <= 0;
forever #(CLOCK_PERIOD/2) clk <= ~clk; // Forever toggle the clock
end
// Set up the inputs to the design. Each line is a clock cycle.
initial begin
@(posedge clk);
reset <= 1; @(posedge clk); // Always reset FSMs at start // two clock cycles to check alternating test
@(posedge clk);
reset <= 0; @(posedge clk); // two clock cycles to check alternating test
@(posedge clk);
@(posedge clk);
@(posedge clk);
SW <= 2'b00;  @(posedge clk);
@(posedge clk);
@(posedge clk);
@(posedge clk);
SW <= 2'b01;  @(posedge clk);
@(posedge clk);
@(posedge clk);
@(posedge clk);
SW <= 2'b10; @(posedge clk);
@(posedge clk);
@(posedge clk);
@(posedge clk);
SW <= 2'b11; @(posedge clk);
@(posedge clk);
@(posedge clk);
@(posedge clk);
$stop; // End the simulation.
end
endmodule

src/test/simple.vcd
$date
	Fri Jul 19 14:53:14 2024
$end
$version
	Icarus Verilog
$end
$timescale
	1ps
$end
$scope module simple_testbench $end
$var wire 3 ! LEDR [2:0] $end
$var parameter 32 " CLOCK_PERIOD $end
$var reg 2 # SW [1:0] $end
$var reg 1 $ clk $end
$var reg 1 % reset $end
$scope module dut $end
$var wire 2 & SW [1:0] $end
$var wire 1 $ clk $end
$var wire 1 % reset $end
$var reg 3 ' LEDR [2:0] $end
$var reg 3 ( ns [2:0] $end
$var reg 3 ) ps [2:0] $end
$upscope $end
$upscope $end
$enddefinitions $end
$comment Show the parameter values. $end
$dumpall
b1100100 "
$end
#0
$dumpvars
bx )
bx (
bx '
bx &
x%
0$
bx #
bx !
$end
#50000
1%
1$
#100000
0$
#150000
b10 (
b101 )
1$
#200000
0$
#250000
b101 !
b101 '
0%
1$
#300000
0$
#350000
b101 (
b10 )
1$
#400000
0$
#450000
b10 (
b10 !
b10 '
b101 )
1$
#500000
0$
#550000
b101 (
b101 !
b101 '
b10 )
1$
#600000
0$
#650000
b10 (
b10 !
b10 '
b101 )
b0 #
b0 &
1$
#700000
0$
#750000
b101 (
b101 !
b101 '
b10 )
1$
#800000
0$
#850000
b10 (
b10 !
b10 '
b101 )
1$
#900000
0$
#950000
b101 (
b101 !
b101 '
b10 )
1$
#1000000
0$
#1050000
b1 (
b10 !
b10 '
b101 )
b1 #
b1 &
1$
#1100000
0$
#1150000
b10 (
b101 !
b101 '
b1 )
1$
#1200000
0$
#1250000
b100 (
b1 !
b1 '
b10 )
1$
#1300000
0$
#1350000
b1 (
b10 !
b10 '
b100 )
1$
#1400000
0$
#1450000
b100 (
b100 !
b100 '
b1 )
b10 #
b10 &
1$
#1500000
0$
#1550000
b10 (
b1 !
b1 '
b100 )
1$
#1600000
0$
#1650000
b1 (
b100 !
b100 '
b10 )
1$
#1700000
0$
#1750000
b100 (
b10 !
b10 '
b1 )
1$
#1800000
0$
#1850000
b101 (
b1 !
b1 '
b100 )
b11 #
b11 &
1$
#1900000
0$
#1950000
b10 (
b100 !
b100 '
b101 )
1$
#2000000
0$
#2050000
b101 (
b101 !
b101 '
b10 )
1$
#2100000
0$
#2150000
b10 (
b10 !
b10 '
b101 )
1$
